memx/__init__.py
memx/engine/__init__.py
memx/engine/mongodb.py
memx/engine/postgres.py
memx/engine/redis.py
memx/engine/sqlite.py
memx/memory/__init__.py
memx/memory/mongodb.py
memx/memory/postgres.py
memx/memory/redis.py
memx/memory/simple.py
memx/memory/sqlite.py
memx/models/__init__.py
memx/models/sql.py
memx/services/__init__.py
memx/services/sql_service.py
memx/utils/__init__.py
memx/utils/sql.py
memx_ai-0.1.13.data/data/README.md
memx_ai-0.1.13.dist-info/METADATA
memx_ai-0.1.13.dist-info/WHEEL
memx_ai-0.1.13.dist-info/licenses/LICENSE
memx_ai-0.1.13.dist-info/RECORD
