Metadata-Version: 2.4
Name: memx-ai
Version: 0.1.13
Summary: Lightweight and extensible memory layer for LLMs
Author-email: Pablo Galilea <pgalilea@me.com>
License-Expression: MIT
License-File: LICENSE
Classifier: Development Status :: 3 - Alpha
Classifier: Intended Audience :: Developers
Classifier: License :: OSI Approved :: MIT License
Classifier: Operating System :: OS Independent
Classifier: Programming Language :: Python :: 3
Classifier: Programming Language :: Python :: 3.10
Classifier: Programming Language :: Python :: 3.11
Classifier: Programming Language :: Python :: 3.12
Classifier: Programming Language :: Python :: 3.13
Classifier: Topic :: Database :: Database Engines/Servers
Classifier: Topic :: Scientific/Engineering :: Artificial Intelligence
Classifier: Topic :: Software Development :: Libraries :: Python Modules
Classifier: Typing :: Typed
Requires-Python: >=3.11
Requires-Dist: aiofiles>=25.1.0
Requires-Dist: orjson>=3.11.4
Requires-Dist: typing-extensions>=4.15.0
Provides-Extra: all
Requires-Dist: aiosqlite>=0.21.0; extra == 'all'
Requires-Dist: psycopg>=3.2.12; extra == 'all'
Requires-Dist: pymongo>=4.15.3; extra == 'all'
Requires-Dist: redis>=7.0.1; extra == 'all'
Requires-Dist: sqlalchemy[asyncio,postgresql-psycopg]>=2.0.44; extra == 'all'
Requires-Dist: sqlalchemy[asyncio]>=2.0.44; extra == 'all'
Provides-Extra: mongodb
Requires-Dist: pymongo>=4.15.3; extra == 'mongodb'
Provides-Extra: postgres
Requires-Dist: psycopg>=3.2.12; extra == 'postgres'
Requires-Dist: sqlalchemy[asyncio,postgresql-psycopg]>=2.0.44; extra == 'postgres'
Provides-Extra: redis
Requires-Dist: redis>=7.0.1; extra == 'redis'
Provides-Extra: sqlite
Requires-Dist: aiosqlite>=0.21.0; extra == 'sqlite'
Requires-Dist: sqlalchemy[asyncio]>=2.0.44; extra == 'sqlite'
